reducer/__init__.py
reducer/_version.py
reducer/astro_gui.py
reducer/core.py
reducer/gui.py
reducer/image_browser.py
reducer/notebook_dir.py
reducer/reducer-template.ipynb
reducer/data/image_metadata.csv
reducer/data/mini_versions.tbz2
reducer-0.8.1.data/data/share/jupyter/jupyter_app_launcher/jp_app_launcher_reducer.yaml
reducer-0.8.1.data/data/share/jupyter/reducer/reducer-template.ipynb
reducer-0.8.1.dist-info/METADATA
reducer-0.8.1.dist-info/WHEEL
reducer-0.8.1.dist-info/entry_points.txt
reducer-0.8.1.dist-info/licenses/LICENSE.rst
reducer-0.8.1.dist-info/RECORD
