Metadata-Version: 2.3
Name: reducer
Version: 0.8.1
Summary: Process FITS files
Project-URL: Homepage, http://reducer.readthedocs.org
Author-email: Matt Craig <mcraig@mnstate.edu>
License-Expression: BSD-3-Clause
License-File: LICENSE.rst
Classifier: Development Status :: 4 - Beta
Classifier: Intended Audience :: Science/Research
Classifier: License :: OSI Approved :: BSD License
Classifier: Programming Language :: Python :: 2.7
Classifier: Programming Language :: Python :: 3
Classifier: Topic :: Scientific/Engineering :: Astronomy
Requires-Dist: astropy>=4.0
Requires-Dist: ccdproc>=2
Requires-Dist: dask
Requires-Dist: ipyautoui
Requires-Dist: ipywidgets>=7.5
Requires-Dist: jupyter-app-launcher
Requires-Dist: matplotlib
Requires-Dist: msumastro>=1
Requires-Dist: numpy
Requires-Dist: scikit-image
Requires-Dist: scipy
Provides-Extra: docs
Requires-Dist: numpydoc; extra == 'docs'
Requires-Dist: sphinx-argparse; extra == 'docs'
Requires-Dist: sphinx-rtd-theme; extra == 'docs'
